{
  "mode": "replay",
  "symbol": "300442.SZ",
  "symbol_name": "润泽科技",
  "trade_date": "2026-03-23",
  "lookback_days": 26,
  "adapter": "tradingagents-cn",
  "account_decision_context": {
    "trade_date": "2026-03-23",
    "symbol": "300442.SZ",
    "symbol_name": "润泽科技",
    "account_cash": 7304372.349999997,
    "account_nav": 32331429.959999997,
    "current_position_quantity": 78271,
    "current_position_average_cost": 85.53914056522669,
    "current_position_last_price": 85.31,
    "current_position_market_value": 6677299.01,
    "sellable_quantity": 78271,
    "blocked_quantity": 0,
    "portfolio_positions": [
      {
        "symbol": "002015.SZ",
        "name": "协鑫能科",
        "quantity": 249238,
        "average_cost": 20.20214962861553,
        "last_price": 19.0,
        "market_value": 4735522.0
      },
      {
        "symbol": "002906.SZ",
        "name": "华阳装备（暂映射华阳集团）",
        "quantity": 63100,
        "average_cost": 32.0,
        "last_price": 26.84,
        "market_value": 1693604.0
      },
      {
        "symbol": "300442.SZ",
        "name": "润泽科技",
        "quantity": 78271,
        "average_cost": 85.53914056522669,
        "last_price": 85.31,
        "market_value": 6677299.01
      },
      {
        "symbol": "600362.SS",
        "name": "江西铜业",
        "quantity": 112048,
        "average_cost": 43.97121662144796,
        "last_price": 42.45,
        "market_value": 4756437.600000001
      },
      {
        "symbol": "603986.SS",
        "name": "兆易创新",
        "quantity": 14700,
        "average_cost": 258.0,
        "last_price": 273.35,
        "market_value": 4018245.0000000005
      },
      {
        "symbol": "688525.SS",
        "name": "佰维存储",
        "quantity": 13982,
        "average_cost": 228.6905115929422,
        "last_price": 225.0,
        "market_value": 3145950.0
      }
    ]
  }
}