{
  "mode": "replay",
  "run_id": "cn_real_historical_1m_portfolio_v5_datalayer_backup_20260413",
  "symbol": "300442.SZ",
  "symbol_name": "润泽科技",
  "trade_date": "2026-03-13",
  "analysis_id": "replay-300442.SZ-2026-03-13",
  "action": "hold",
  "confidence": 0.75,
  "signal_confidence": 0.75,
  "size_hint": 0.3,
  "target_position_pct": 0.5,
  "execution_price": 83.54,
  "starting_cash": 3941593.3299999963,
  "cash": 9.049999996088445,
  "starting_nav": 33242663.29,
  "nav": 33242663.29,
  "starting_quantity": 0,
  "position_quantity": 47182,
  "filled_quantity": 47182,
  "filled_gross_value": 3941584.2800000003,
  "filled_notional": 3941584.2800000003,
  "execution_blockers": [],
  "reason_summary": "空仓状态下，当前87.92元不具备建仓条件。盈利质量存疑（净利率118%异常、扣非ROE仅11.51%）、PB 10倍高估、PE_TTM 27倍安全边际不足；技术面均线空头排列、下跌趋势未改；PE静值76倍vs PE_TTM 27倍的巨大差异表明四季度净利润或有重大变化，但未经年报验证。建议等待：1）价格回落至80-82元企稳并出现底部形态；2）2025年年报确认盈利质量后再建仓。当前账户未持有该标的，结合研究结论中的观望策略，空仓者应保持耐心。",
  "order_contract_status": "partial_fallback",
  "order_contract_source": "processed_decision",
  "order_contract_notes": [
    "target_position_pct_fallback_from_text",
    "size_hint_fallback_from_text"
  ],
  "t_plus_one": {
    "enabled": true,
    "pre_trade_sellable_quantity": 0,
    "pre_trade_blocked_quantity": 0,
    "post_trade_sellable_quantity": 0,
    "post_trade_blocked_quantity": 47182,
    "blocked_sell_detected": false
  },
  "analysis_integrity": {
    "ok": true,
    "checks": {
      "final_trade_decision": {
        "length": 3230,
        "min_length": 100,
        "length_ok": true,
        "identity_ok": true,
        "data_quality_ok": true,
        "expected_company_name": "润泽科技",
        "ok": true
      },
      "market_report": {
        "length": 1372,
        "min_length": 200,
        "length_ok": true,
        "identity_ok": true,
        "data_quality_ok": true,
        "expected_company_name": "润泽科技",
        "ok": true
      },
      "sentiment_report": {
        "length": 2849,
        "min_length": 200,
        "length_ok": true,
        "identity_ok": true,
        "data_quality_ok": true,
        "expected_company_name": "润泽科技",
        "ok": true
      },
      "news_report": {
        "length": 2112,
        "min_length": 300,
        "length_ok": true,
        "identity_ok": true,
        "data_quality_ok": true,
        "expected_company_name": "润泽科技",
        "ok": true
      },
      "fundamentals_report": {
        "length": 3069,
        "min_length": 200,
        "length_ok": true,
        "identity_ok": true,
        "data_quality_ok": true,
        "expected_company_name": "润泽科技",
        "ok": true
      }
    },
    "selected_analysts": [
      "market",
      "social",
      "news",
      "fundamentals"
    ]
  },
  "historical_data_diagnostics": {
    "symbol": "300442.SZ",
    "graph_symbol": "300442",
    "trade_date": "2026-03-13",
    "research_cutoff_time": "14:45",
    "company_name": "润泽科技",
    "minute_points_visible": 1,
    "news_lookback_days": 30,
    "news": {
      "provider": "AKShare巨潮资讯历史公告",
      "payload_cached": true,
      "payload_length": 2484,
      "news_count": 10,
      "report_length": 2112,
      "strict_non_empty": true
    },
    "sentiment": {
      "mode": "historical_finance_news_proxy",
      "proxy_provider": "AKShare巨潮资讯历史公告",
      "report_length": 2849,
      "identity_ok": true,
      "raw_social_api_available": false
    },
    "fundamentals": {
      "provider": "Tushare日度估值截面 + Tushare财务指标 + AKShare巨潮资讯历史公告",
      "payload_cached": true,
      "payload_length": 3121,
      "report_length": 3069,
      "data_quality_ok": true
    }
  },
  "runtime_skip": {},
  "news_provider": "AKShare巨潮资讯历史公告",
  "news_count": 10,
  "fundamentals_provider": "Tushare日度估值截面 + Tushare财务指标 + AKShare巨潮资讯历史公告",
  "minute_points_visible": 1,
  "strategy_plan_path": "2026-03-13/300442.SZ/strategy_plan.md",
  "strategy_rollup_path": "by_symbol/300442.SZ/strategy.md",
  "strategy_excerpt": "# 润泽科技（300442）辩论评估与投资决策 ## 一、辩论总结 ### 激进分析师核心论点 1. **数据时效性质疑**：扣非ROE 11.51%是6个月前的旧数据，期间可能已发生重大变化 2. **现金流论证**：经营现金流/股1.69元证明公司现金流健康 3. **资本运作信心**：可转债重组预案已获股东大会通过，管理层回购彰显信心 4. **估值…",
  "execution_audit": {
    "strategy_excerpt": "# 润泽科技（300442）辩论评估与投资决策 ## 一、辩论总结 ### 激进分析师核心论点 1. **数据时效性质疑**：扣非ROE 11.51%是6个月前的旧数据，期间可能已发生重大变化 2. **现金流论证**：经营现金流/股1.69元证明公司现金流健康 3. **资本运作信心**：可转债重组预案已获股东大会通过，管理层回购彰显信心 4. **估值…",
    "signal_action": "hold",
    "signal_size_hint": 0.3,
    "signal_target_position_pct": 0.5,
    "expected_trade_direction": "buy",
    "actual_trade_direction": "buy",
    "filled_quantity": 47182,
    "trade_count": 1,
    "starting_quantity": 0,
    "ending_quantity": 47182,
    "execution_blockers": [],
    "status": "consistent",
    "reason": "signal and actual fill direction match"
  }
}