{
  "mode": "replay",
  "symbol": "688525.SS",
  "symbol_name": "佰维存储",
  "trade_date": "2026-03-27",
  "lookback_days": 26,
  "adapter": "tradingagents-cn",
  "account_decision_context": {
    "trade_date": "2026-03-27",
    "symbol": "688525.SS",
    "symbol_name": "佰维存储",
    "account_cash": 62.79999999597203,
    "account_nav": 32470223.639999997,
    "current_position_quantity": 34272,
    "current_position_average_cost": 234.78218175456692,
    "current_position_last_price": 238.4,
    "current_position_market_value": 8170444.8,
    "sellable_quantity": 34272,
    "blocked_quantity": 0,
    "portfolio_positions": [
      {
        "symbol": "002015.SZ",
        "name": "协鑫能科",
        "quantity": 123235,
        "average_cost": 20.20214962861553,
        "last_price": 17.76,
        "market_value": 2188653.6
      },
      {
        "symbol": "002906.SZ",
        "name": "华阳装备（暂映射华阳集团）",
        "quantity": 63100,
        "average_cost": 32.0,
        "last_price": 27.4,
        "market_value": 1728940.0
      },
      {
        "symbol": "300442.SZ",
        "name": "润泽科技",
        "quantity": 97151,
        "average_cost": 84.88950610330195,
        "last_price": 83.45,
        "market_value": 8107250.95
      },
      {
        "symbol": "600362.SS",
        "name": "江西铜业",
        "quantity": 193041,
        "average_cost": 44.07140146393771,
        "last_price": 43.89,
        "market_value": 8472569.49
      },
      {
        "symbol": "603986.SS",
        "name": "兆易创新",
        "quantity": 14700,
        "average_cost": 258.0,
        "last_price": 258.66,
        "market_value": 3802302.0000000005
      },
      {
        "symbol": "688525.SS",
        "name": "佰维存储",
        "quantity": 34272,
        "average_cost": 234.78218175456692,
        "last_price": 238.4,
        "market_value": 8170444.8
      }
    ]
  }
}