{
  "action": "hold",
  "symbol": "002015.SZ",
  "symbol_name": "协鑫能科",
  "confidence": 0.75,
  "size_hint": 0.11,
  "reason_summary": "当前持仓842927股（占比51.3%），持仓成本20.20元，账面浮盈约60万元。研究结论明确：PE_TTM 52.33倍处高估值区间，股息率仅0.47%，管理层主动发布补充风险提示，20元整数关口仅距现价0.07元但尚未有效跌破。回调尚未充分（仅回撤约10%），风险收益比不利（向上约5.6%空间vs向下10-15%空间）。当前未触发硬止损线（收盘跌破20元），建议持有但适度降仓，理由：持仓过重+支撑脆弱+赔率不佳。",
  "source_artifact_id": "replay-002015.SZ-2026-03-20",
  "target_position_pct": 0.4,
  "order_plan": {
    "schema_version": "v1",
    "contract_status": "structured",
    "contract_source": "processed_decision",
    "action": "hold",
    "confidence": 0.75,
    "risk_score": 0.6,
    "reasoning": "当前持仓842927股（占比51.3%），持仓成本20.20元，账面浮盈约60万元。研究结论明确：PE_TTM 52.33倍处高估值区间，股息率仅0.47%，管理层主动发布补充风险提示，20元整数关口仅距现价0.07元但尚未有效跌破。回调尚未充分（仅回撤约10%），风险收益比不利（向上约5.6%空间vs向下10-15%空间）。当前未触发硬止损线（收盘跌破20元），建议持有但适度降仓，理由：持仓过重+支撑脆弱+赔率不佳。",
    "size_hint": 0.11,
    "target_position_pct": 0.4,
    "target_price": null,
    "buy_below_price": null,
    "sell_above_price": null,
    "stop_loss_price": 19.8,
    "take_profit_price": 21.5,
    "valid_until": "2026-03-27",
    "notes": []
  }
}