{
  "mode": "replay",
  "run_id": "cn_real_historical_1m_portfolio_v6_holdings_context_backup_20260413",
  "symbol": "600362.SS",
  "symbol_name": "江西铜业",
  "trade_date": "2026-03-23",
  "analysis_id": "replay-600362.SS-2026-03-23",
  "action": "sell",
  "confidence": 0.82,
  "signal_confidence": 0.82,
  "size_hint": 0.5,
  "target_position_pct": 0.25,
  "execution_price": 42.45,
  "starting_cash": 6645057.020000007,
  "cash": 14663564.870000008,
  "starting_nav": 32550323.54000001,
  "nav": 32550323.54000001,
  "starting_quantity": 380591,
  "position_quantity": 191698,
  "filled_quantity": 188893,
  "filled_gross_value": 8018507.850000001,
  "filled_notional": 8018507.850000001,
  "execution_blockers": [],
  "reason_summary": "决策委员会明确建议卖出。当前持仓成本45.84元vs现价42.45元，亏损约7.4%。技术面处于加速下跌趋势，今日跌4%，均线空头排列无企稳信号，43元支撑已破，下一关键支撑42元。基本面净利润增速成色存疑(净利率仅1.64%)，毛利率净利率双降，速动比率0.8212<1，铜价下行时负债结构极度脆弱。机构在利好公布后持续抛售(3月9日至今日跌近17.6%)，smart money撤退信号明确。持有风险大于机会，止损位42元，跌破将测试38-40元。建议分批减仓而非一次性清仓，可先减50%观察。",
  "order_contract_status": "structured",
  "order_contract_source": "processed_decision",
  "order_contract_notes": [],
  "t_plus_one": {
    "enabled": true,
    "pre_trade_sellable_quantity": 380591,
    "pre_trade_blocked_quantity": 0,
    "post_trade_sellable_quantity": 191698,
    "post_trade_blocked_quantity": 0,
    "blocked_sell_detected": false
  },
  "analysis_integrity": {
    "ok": true,
    "checks": {
      "final_trade_decision": {
        "length": 3259,
        "min_length": 100,
        "length_ok": true,
        "identity_ok": true,
        "data_quality_ok": true,
        "expected_company_name": "江西铜业",
        "ok": true
      },
      "market_report": {
        "length": 1735,
        "min_length": 200,
        "length_ok": true,
        "identity_ok": true,
        "data_quality_ok": true,
        "expected_company_name": "江西铜业",
        "ok": true
      },
      "sentiment_report": {
        "length": 2807,
        "min_length": 200,
        "length_ok": true,
        "identity_ok": true,
        "data_quality_ok": true,
        "expected_company_name": "江西铜业",
        "ok": true
      },
      "news_report": {
        "length": 2045,
        "min_length": 300,
        "length_ok": true,
        "identity_ok": true,
        "data_quality_ok": true,
        "expected_company_name": "江西铜业",
        "ok": true
      },
      "fundamentals_report": {
        "length": 4961,
        "min_length": 200,
        "length_ok": true,
        "identity_ok": true,
        "data_quality_ok": true,
        "expected_company_name": "江西铜业",
        "ok": true
      }
    },
    "selected_analysts": [
      "market",
      "social",
      "news",
      "fundamentals"
    ]
  },
  "historical_data_diagnostics": {
    "symbol": "600362.SS",
    "graph_symbol": "600362",
    "trade_date": "2026-03-23",
    "research_cutoff_time": "14:45",
    "company_name": "江西铜业",
    "minute_points_visible": 1,
    "news_lookback_days": 30,
    "news": {
      "provider": "AKShare巨潮资讯历史公告",
      "payload_cached": true,
      "payload_length": 1760,
      "news_count": 7,
      "report_length": 2045,
      "strict_non_empty": true
    },
    "sentiment": {
      "mode": "historical_finance_news_proxy",
      "proxy_provider": "AKShare巨潮资讯历史公告",
      "report_length": 2807,
      "identity_ok": true,
      "raw_social_api_available": false
    },
    "fundamentals": {
      "provider": "Tushare日度估值截面 + Tushare财务指标 + AKShare巨潮资讯历史公告",
      "payload_cached": true,
      "payload_length": 2896,
      "report_length": 4961,
      "data_quality_ok": true
    }
  },
  "runtime_skip": {},
  "news_provider": "AKShare巨潮资讯历史公告",
  "news_count": 7,
  "fundamentals_provider": "Tushare日度估值截面 + Tushare财务指标 + AKShare巨潮资讯历史公告",
  "minute_points_visible": 1,
  "strategy_plan_path": "2026-03-23/600362.SS/strategy_plan.md",
  "strategy_rollup_path": "by_symbol/600362.SS/strategy.md",
  "strategy_excerpt": "# 风险管理委员会主席决策报告 ## 核心决策：**卖出** --- ## 一、辩论评估：核心分歧的本质 经过全面审视三位分析师的论点，我发现这场辩论的核心分歧在于：**对当前下跌性质的判断，以及对净利润增长成色的评估**。 **激进分析师的逻辑链**：机构在利好公布后持续抛售 → 这是smart money撤退信号 → 下跌不是情绪性的，是基本面的反应 …",
  "execution_audit": {
    "strategy_excerpt": "# 风险管理委员会主席决策报告 ## 核心决策：**卖出** --- ## 一、辩论评估：核心分歧的本质 经过全面审视三位分析师的论点，我发现这场辩论的核心分歧在于：**对当前下跌性质的判断，以及对净利润增长成色的评估**。 **激进分析师的逻辑链**：机构在利好公布后持续抛售 → 这是smart money撤退信号 → 下跌不是情绪性的，是基本面的反应 …",
    "signal_action": "sell",
    "signal_size_hint": 0.5,
    "signal_target_position_pct": 0.25,
    "expected_trade_direction": "sell",
    "actual_trade_direction": "sell",
    "filled_quantity": 188893,
    "trade_count": 1,
    "starting_quantity": 380591,
    "ending_quantity": 191698,
    "execution_blockers": [],
    "status": "consistent",
    "reason": "signal and actual fill direction match"
  }
}