{
  "action": "sell",
  "symbol": "002015.SZ",
  "symbol_name": "协鑫能科",
  "confidence": 0.75,
  "size_hint": 0.0,
  "reason_summary": "研究报告明确建议卖出。技术面空头排列未改，涨停后从17.25元回落至16.36元（报告撰写时）已反映做多动能不足。当前现价17.35元已接近短期压力位17.25-17.30元区间，应借反弹择机减仓。基本面核心数据（PE/PB/ROE）持续缺失无法支撑估值，担保和质押活动频繁暗示资金链压力。当前持仓浮盈约4.4%（成本16.62，现价17.35），建议锁定收益。",
  "source_artifact_id": "replay-002015.SZ-2026-04-07",
  "target_position_pct": 0.0,
  "order_plan": {
    "schema_version": "v1",
    "contract_status": "structured",
    "contract_source": "processed_decision",
    "action": "sell",
    "confidence": 0.75,
    "risk_score": 0.7,
    "reasoning": "研究报告明确建议卖出。技术面空头排列未改，涨停后从17.25元回落至16.36元（报告撰写时）已反映做多动能不足。当前现价17.35元已接近短期压力位17.25-17.30元区间，应借反弹择机减仓。基本面核心数据（PE/PB/ROE）持续缺失无法支撑估值，担保和质押活动频繁暗示资金链压力。当前持仓浮盈约4.4%（成本16.62，现价17.35），建议锁定收益。",
    "size_hint": null,
    "target_position_pct": 0.0,
    "target_price": null,
    "buy_below_price": null,
    "sell_above_price": null,
    "stop_loss_price": 16.0,
    "take_profit_price": 17.3,
    "valid_until": "",
    "notes": [
      "size_hint_unused_target_rebalance"
    ]
  }
}